monerorpc/__init__.py
monerorpc/authproxy.py
python_monerorpc-0.6.2.dist-info/LICENSE
python_monerorpc-0.6.2.dist-info/METADATA
python_monerorpc-0.6.2.dist-info/WHEEL
python_monerorpc-0.6.2.dist-info/top_level.txt
python_monerorpc-0.6.2.dist-info/RECORD
