Metadata-Version: 2.1
Name: python-monerorpc
Version: 0.6.2
Summary: Enhanced version of python-jsonrpc for Monero (monerod, monero-wallet-rpc).
Home-page: https://www.github.com/monero-ecosystem/python-monerorpc
Author: Norman Moeschter-Schenck
Author-email: <norman.moeschter@gmail.com>
Maintainer: Norman Moeschter-Schenck
Maintainer-email: <norman.moeschter@gmail.com>
License: UNKNOWN
Download-URL: https://github.com/monero-ecosystem/python-monerorpc/archive/v0.6.2.tar.gz
Platform: UNKNOWN
Classifier: License :: OSI Approved :: MIT License
Classifier: Operating System :: OS Independent
Classifier: Programming Language :: Python :: 3.6
Classifier: Programming Language :: Python :: 3.7
Requires-Dist: requests (>=2.23.0)
